tiozin/__init__.py
tiozin/app.py
tiozin/cli.py
tiozin/config.py
tiozin/env.py
tiozin/exceptions.py
tiozin/lifecycle.py
tiozin/logs.py
tiozin/api/__init__.py
tiozin/api/loggable.py
tiozin/api/plugin.py
tiozin/api/registry.py
tiozin/api/typehint.py
tiozin/api/metadata/docs.py
tiozin/api/metadata/input_manifest.py
tiozin/api/metadata/job_manifest.py
tiozin/api/metadata/manifest.py
tiozin/api/metadata/output_manifest.py
tiozin/api/metadata/runner_manifest.py
tiozin/api/metadata/transform_manifest.py
tiozin/api/processors/context.py
tiozin/api/processors/input.py
tiozin/api/processors/job.py
tiozin/api/processors/output.py
tiozin/api/processors/runner.py
tiozin/api/processors/transform.py
tiozin/api/registries/job_registry.py
tiozin/api/registries/lineage_registry.py
tiozin/api/registries/metric_registry.py
tiozin/api/registries/schema_registry.py
tiozin/api/registries/secret_registry.py
tiozin/api/registries/setting_registry.py
tiozin/api/registries/transaction_registry.py
tiozin/assembly/__init__.py
tiozin/assembly/job_builder.py
tiozin/assembly/job_proxy.py
tiozin/assembly/plugin_factory.py
tiozin/assembly/plugin_scanner.py
tiozin/assembly/plugin_template.py
tiozin/assembly/policies.py
tiozin/assembly/proxying.py
tiozin/assembly/registry_factory.py
tiozin/assembly/runner_proxy.py
tiozin/assembly/step_proxy.py
tiozin/assembly/template_context_builder.py
tiozin/family/tio_kernel/__init__.py
tiozin/family/tio_kernel/inputs/__init__.py
tiozin/family/tio_kernel/inputs/noop_input.py
tiozin/family/tio_kernel/jobs/__init__.py
tiozin/family/tio_kernel/jobs/linear_job.py
tiozin/family/tio_kernel/outputs/__init__.py
tiozin/family/tio_kernel/outputs/noop_output.py
tiozin/family/tio_kernel/registries/__init__.py
tiozin/family/tio_kernel/registries/file_job_registry.py
tiozin/family/tio_kernel/registries/noop_lineage_registry.py
tiozin/family/tio_kernel/registries/noop_metric_registry.py
tiozin/family/tio_kernel/registries/noop_schema_registry.py
tiozin-2.0.0.dist-info/METADATA
tiozin-2.0.0.dist-info/WHEEL
tiozin-2.0.0.dist-info/entry_points.txt
tiozin-2.0.0.dist-info/licenses/LICENSE
tiozin-2.0.0.dist-info/RECORD
