Metadata-Version: 2.4
Name: tiozin
Version: 2.0.0
Summary: Tiozin, your friendly ETL framework
Project-URL: Homepage, https://github.com/fdmorison/tiozin
Project-URL: Repository, https://github.com/fdmorison/tiozin
Project-URL: Issues, https://github.com/fdmorison/tiozin/issues
Author-email: Fabricio D'Morison <fabricio.dmorison@gmail.com>
License-Expression: MPL-2.0
License-File: LICENSE
Keywords: data,declarative,etl,framework,pipeline,yaml
Classifier: Development Status :: 5 - Production/Stable
Classifier: License :: OSI Approved :: Mozilla Public License 2.0 (MPL 2.0)
Classifier: Programming Language :: Python :: 3
Classifier: Programming Language :: Python :: 3.11
Requires-Python: >=3.11
Requires-Dist: environs~=14.3
Requires-Dist: fsspec~=2026.1
Requires-Dist: jinja2~=3.1.6
Requires-Dist: pendulum~=3.1.0
Requires-Dist: pydantic~=2.12
Requires-Dist: ruamel-yaml~=0.18
Requires-Dist: single-source~=0.4
Requires-Dist: structlog~=25.5
Requires-Dist: typer~=0.20
Requires-Dist: uuid-utils~=0.12
Requires-Dist: wrapt~=2.0.1
Provides-Extra: aws
Requires-Dist: s3fs~=2026.1; extra == 'aws'
Provides-Extra: azure
Requires-Dist: adlfs~=2025.8; extra == 'azure'
Provides-Extra: gcp
Requires-Dist: gcsfs~=2026.1; extra == 'gcp'
Provides-Extra: tio-spark
Requires-Dist: pyspark<4.0.0,>=3.5.0; extra == 'tio-spark'
